PyQE_Solver-4.0.0.dist-info/DESCRIPTION.rst
PyQE_Solver-4.0.0.dist-info/METADATA
PyQE_Solver-4.0.0.dist-info/RECORD
PyQE_Solver-4.0.0.dist-info/WHEEL
PyQE_Solver-4.0.0.dist-info/metadata.json
PyQE_Solver-4.0.0.dist-info/top_level.txt
QE_Solver/Solver.py
QE_Solver/__init__.py
