Metadata-Version: 2.0
Name: PyQE-Solver
Version: 4.0.0
Summary: Quadratic Equation Solver
Home-page: https://github.com/PS218909/ROOT
Author: Piyush
Author-email: pyushsomani97@gmail.com
License: UNKNOWN
Platform: UNKNOWN
Requires-Python: >=3.6
